Workbook

Sheet Forecast
A1: Consumo privado | B1: Retorno do capital | C1: Trabalho | D1: Capital privado | E1: Investimento privado | F1: Produto | G1: Taxa de salário | H1: Taxa de retorno dos ativos financeiros | I1: Produtividade Total dos Fatores | J1: Dívida bruta do governo | K1: Receita fiscal | L1: Taxa de imposto sobre consumo | M1: Taxa de imposto sobre salário | N1: Taxa de imposto sobre a renda do capital | O1: Imposto Lump-Sum | P1: Gasto primário | Q1: Consumo público corrente | R1: Investimento público | S1: Capital público | T1: Resultado primário | U1: Ajuste Estoque-Fluxo | V1: Dívida como proporção do PIB | W1: Gasto primário como proporção do PIB | X1: Receita fiscal como proporção do PIB | Y1: Resultado primário como proporção do PIB | Z1: Crescimento do PIB
A2: 0.48415649 | B2: 0.09883107 | C2: 0.46802539 | D2: 4.7981408 | E2: 0.15798132 | F2: 1.0648804 | G2: 1.2556814 | H2: 0.046877728 | I2: 0.99497309 | J2: 0.92978684 | K2: 0.42046242 | L2: 0.17256467 | M2: 0.15012201 | N2: 0.15036714 | O2: 0.17703336 | P2: 0.42274258 | Q2: 0.41850897 | R2: 0.0042336159 | S2: 0.11298525 | T2: -0.0022801603 | U2: -0.0414548 | V2: 0.8728384 | W2: 0.3970472 | X2: 0.3948536 | Y2: -0.0021936 | Z2: 0.033938883
A3: 0.48560506 | B3: 0.09925113 | C3: 0.46845888 | D3: 4.7803181 | E3: 0.16196559 | F3: 1.0640591 | G3: 1.2535951 | H3: 0.047178451 | I3: 0.99588027 | J3: 0.93049111 | K3: 0.41779848 | L3: 0.16619716 | M3: 0.15005012 | N3: 0.15015002 | O3: 0.17742751 | P3: 0.41648844 | Q3: 0.41225485 | R3: 0.0042335898 | S3: 0.11298524 | T3: 0.0013100462 | U3: -0.0414548 | V3: 0.87421921 | W3: 0.39143841 | X3: 0.39264191 | Y3: 0.0012035004 | Z3: 0.022824009
A4: 0.48562091 | B4: 0.099594252 | C4: 0.46888068 | D4: 4.7659111 | E4: 0.16471339 | F4: 1.0635442 | G4: 1.2518963 | H4: 0.047424712 | I4: 0.99662373 | J4: 0.92943908 | K4: 0.41660449 | L4: 0.16366746 | M4: 0.15002059 | N4: 0.1500613 | O4: 0.17756913 | P4: 0.4132099 | Q4: 0.40897632 | R4: 0.0042335776 | S4: 0.11298521 | T4: 0.0033945942 | U4: -0.0414548 | V4: 0.8736737 | W4: 0.38852901 | X4: 0.39170517 | Y4: 0.003176157 | Z4: 0.023113519
A5: 0.48512495 | B5: 0.099879611 | C5: 0.46928161 | D5: 4.7539251 | E5: 0.16659457 | F5: 1.0632108 | G5: 1.2504633 | H5: 0.047631292 | I5: 0.99723303 | J5: 0.92748751 | K5: 0.41597363 | L5: 0.16266245 | M5: 0.15000846 | N5: 0.15002505 | O5: 0.17757029 | P5: 0.41149123 | Q5: 0.40725765 | R5: 0.0042335719 | S5: 0.11298518 | T5: 0.004482406 | U5: -0.0414548 | V5: 0.87212024 | W5: 0.38702708 | X5: 0.39123305 | Y5: 0.0042059702 | Z5: 0.023284952
A6: 0.48447489 | B6: 0.10012086 | C6: 0.46965395 | D6: 4.7437017 | E6: 0.16790801 | F6: 1.0629732 | G6: 1.2492166 | H6: 0.047807664 | I6: 0.99773236 | J6: 0.92515336 | K6: 0.41556037 | L6: 0.16226318 | M6: 0.15000348 | N6: 0.15001024 | O6: 0.17749757 | P6: 0.41059027 | Q6: 0.4063567 | R6: 0.0042335692 | S6: 0.11298515 | T6: 0.0049701028 | U6: -0.0414548 | V6: 0.87012181 | W6: 0.3862627 | X6: 0.3909309 | Y6: 0.0046681974 | Z6: 0.023375523
A7: 0.48380629 | B7: 0.10032763 | C7: 0.46999418 | D7: 4.7348098 | E7: 0.16885654 | F7: 1.0627808 | G7: 1.2481062 | H7: 0.047960205 | I7: 0.99814159 | J7: 0.92272782 | K7: 0.41523616 | L7: 0.16210456 | M7: 0.15000143 | N7: 0.15000418 | O7: 0.17738995 | P7: 0.41011797 | Q7: 0.4058844 | R7: 0.0042335679 | S7: 0.11298512 | T7: 0.0051181976 | U7: -0.0414548 | V7: 0.86799766 | W7: 0.3858868 | X7: 0.39069609 | Y7: 0.0048092851 | Z7: 0.023418233
A8: 0.48316765 | B8: 0.1005068 | C8: 0.47030208 | D8: 4.7269631 | E8: 0.16956847 | F8: 1.0626065 | G8: 1.247101 | H8: 0.048093429 | I8: 0.99847697 | J8: 0.92036518 | K8: 0.41495463 | L8: 0.16204154 | M8: 0.15000059 | N8: 0.15000171 | O8: 0.17726962 | P8: 0.40987038 | Q8: 0.40563681 | R8: 0.0042335673 | S8: 0.11298509 | T8: 0.0050842549 | U8: -0.0414548 | V8: 0.86591718 | W8: 0.3857166 | X8: 0.39049487 | Y8: 0.004778269 | Z8: 0.023435323
A9: 0.48257378 | B9: 0.10066341 | C9: 0.47057937 | D9: 4.7199648 | E9: 0.17012286 | F9: 1.0624372 | G9: 1.2461815 | H9: 0.048210673 | I9: 0.99875182 | J9: 0.91814104 | K9: 0.41469956 | L9: 0.1620165 | M9: 0.15000024 | N9: 0.1500007 | O9: 0.17714871 | P9: 0.40974059 | Q9: 0.40550702 | R9: 0.004233567 | S9: 0.11298506 | T9: 0.0049589692 | U9: -0.0414548 | V9: 0.86396318 | W9: 0.38565587 | X9: 0.39031678 | Y9: 0.0046609188 | Z9: 0.023440076
A10: 0.48202682 | B10: 0.10080129 | C10: 0.47082868 | D10: 4.7136742 | E10: 0.17056833 | F10: 1.0622677 | G10: 1.2453345 | H10: 0.048314502 | I10: 0.99897707 | J10: 0.91608759 | K10: 0.41446529 | L10: 0.16200656 | M10: 0.1500001 | N10: 0.15000029 | O10: 0.17703348 | P10: 0.40967255 | Q10: 0.40543898 | R10: 0.0042335669 | S10: 0.11298503 | T10: 0.0047927379 | U10: -0.0414548 | V10: 0.86217069 | W10: 0.38565357 | X10: 0.39015845 | Y10: 0.0045048836 | Z10: 0.023439819
A11: 0.4815244 | B11: 0.10092342 | C11: 0.47105293 | D11: 4.7079862 | E11: 0.17093529 | F11: 1.0620966 | G11: 1.244551 | H11: 0.048406943 | I11: 0.99916167 | J11: 0.91421396 | K11: 0.41424961 | L11: 0.1620026 | M11: 0.15000004 | N11: 0.15000012 | O11: 0.17692686 | P11: 0.40963688 | Q11: 0.40540332 | R11: 0.0042335668 | S11: 0.11298501 | T11: 0.0046127273 | U11: -0.0414548 | V11: 0.86054949 | W11: 0.38568244 | X11: 0.39001828 | Y11: 0.004335839 | Z11: 0.023438314
A12: 0.48106285 | B12: 0.10103217 | C12: 0.47125496 | D12: 4.7028195 | E12: 0.17124336 | F12: 1.0619244 | G12: 1.2438241 | H12: 0.048489632 | I12: 0.99931296 | J12: 0.91251754 | K12: 0.41405129 | L12: 0.16200103 | M12: 0.15000002 | N12: 0.15000005 | O12: 0.17682992 | P12: 0.40961819 | Q12: 0.40538462 | R12: 0.0042335668 | S12: 0.11298498 | T12: 0.0044331017 | U12: -0.0414548 | V12: 0.85909664 | W12: 0.38572774 | X12: 0.3898949 | Y12: 0.0041671646 | Z12: 0.023437319

Sheet Smooth
A1: Consumo privado | B1: Retorno do capital | C1: Trabalho | D1: Capital privado | E1: Investimento privado | F1: Produto | G1: Taxa de salário | H1: Taxa de retorno dos ativos financeiros | I1: Produtividade Total dos Fatores | J1: Dívida bruta do governo | K1: Receita fiscal | L1: Taxa de imposto sobre consumo | M1: Taxa de imposto sobre salário | N1: Taxa de imposto sobre a renda do capital | O1: Imposto Lump-Sum | P1: Gasto primário | Q1: Consumo público corrente | R1: Investimento público | S1: Capital público | T1: Resultado primário | U1: Ajuste Estoque-Fluxo | V1: Dívida como proporção do PIB | W1: Gasto primário como proporção do PIB | X1: Receita fiscal como proporção do PIB | Y1: Resultado primário como proporção do PIB | Z1: Crescimento do PIB
A2: 0.50386873 | B2: 0.10236787 | C2: 0.46959391 | D2: 4.7195047 | E2: 0.21045549 | F2: 1.0704118 | G2: 1.2580429 | H2: 0.049098391 | I2: 1.0115281 | J2: 0.72370343 | K2: 0.38928749 | L2: 0.12470472 | M2: 0.14895177 | N2: 0.14840262 | O2: 0.1661843 | P2: 0.35608756 | Q2: 0.351854 | R2: 0.0042335582 | S2: 0.1129857 | T2: 0.033199932 | U2: -0.0414548 | V2: 0.6733066 | W2: 0.332047 | X2: 0.3633426 | Y2: 0.0312956 | Z2: 0.013852707 | AA2: 0.0061593063 | AB2: 0.043027731 | AC2: 2.8052375e-05 | AD2: 0.069878847 | AE2: 0.0023358928 | AF2: 0.0026661223 | AG2: 0.14115772
A3: 0.46862452 | B3: 0.10230525 | C3: 0.46913479 | D3: 4.7527826 | E3: 0.21011961 | F3: 1.0777328 | G3: 1.2677717 | H3: 0.048895277 | I3: 1.015607 | J3: 0.82321433 | K3: 0.43463024 | L3: 0.21706209 | M3: 0.15190526 | N3: 0.15201341 | O3: 0.16883053 | P3: 0.39898863 | Q3: 0.39475495 | R3: 0.0042336815 | S3: 0.11298577 | T3: 0.035641609 | U3: -0.0414548 | V3: 0.7609506 | W3: 0.3699043 | X3: 0.4034626 | Y3: 0.0335583 | Z3: 0.030517091 | AA3: -0.0089098774 | AB3: -0.14633759 | AC3: -1.8158626e-05 | AD3: -0.079488436 | AE3: -0.0021439554 | AF3: -0.0032354049 | AG3: -0.021441295
A4: 0.51672344 | B4: 0.10032624 | C4: 0.46598544 | D4: 4.7780931 | E4: 0.20339914 | F4: 1.0648387 | G4: 1.2609463 | H4: 0.047673095 | I4: 1.0038806 | J4: 0.76283791 | K4: 0.38236646 | L4: 0.10438676 | M4: 0.14863876 | N4: 0.14758731 | O4: 0.16823738 | P4: 0.3447161 | Q4: 0.34048255 | R4: 0.0042335438 | S4: 0.11298569 | T4: 0.037650363 | U4: -0.0414548 | V4: 0.7151364 | W4: 0.3233407 | X4: 0.3588749 | Y4: 0.0355342 | Z4: 0.011417286 | AA4: 0.028557526 | AB4: -0.032886261 | AC4: 1.4555948e-05 | AD4: 0.0056308732 | AE4: -0.00024004082 | AF4: 0.00015304666 | AG4: 0.044881325
A5: 0.50999463 | B5: 0.10324632 | C5: 0.46917536 | D5: 4.827652 | E5: 0.2285959 | F5: 1.1008452 | G5: 1.2946044 | H5: 0.049265802 | I5: 1.0317378 | J5: 0.75910945 | K5: 0.40540285 | L5: 0.14474215 | M5: 0.14920074 | N5: 0.14916718 | O5: 0.16671638 | P5: 0.36225464 | Q5: 0.35802102 | R5: 0.0042336176 | S5: 0.11298569 | T5: 0.043148208 | U5: -0.0414548 | V5: 0.6802506 | W5: 0.3267459 | X5: 0.3672569 | Y5: 0.040511 | Z5: 0.057620002 | AA5: 0.010295204 | AB5: 0.0043213678 | AC5: 2.006658e-05 | AD5: 0.037022566 | AE5: 0.0013785258 | AF5: 0.001281803 | AG5: 0.042371586
A6: 0.49508696 | B6: 0.10301609 | C6: 0.46838488 | D6: 4.8749107 | E6: 0.22815276 | F6: 1.109771 | G6: 1.3070668 | H6: 0.048966678 | I6: 1.0363055 | J6: 0.75615588 | K6: 0.42776467 | L6: 0.19216632 | M6: 0.15105017 | N6: 0.1509415 | O6: 0.16570577 | P6: 0.38653133 | Q6: 0.38229766 | R6: 0.0042336756 | S6: 0.11298574 | T6: 0.041233338 | U6: -0.0414548 | V6: 0.6696852 | W6: 0.3464195 | X6: 0.3850673 | Y6: 0.0386478 | Z6: 0.032033435 | AA6: 0.015084462 | AB6: 0.029514866 | AC6: 2.7775759e-05 | AD6: 0.0099183019 | AE6: 0.00049219606 | AF6: 0.00015870747 | AG6: 0.011504353
A7: 0.50132002 | B7: 0.10361639 | C7: 0.47092766 | D7: 4.9082259 | E7: 0.21597998 | F7: 1.1267702 | G7: 1.3202567 | H7: 0.049383947 | I7: 1.0448381 | J7: 0.74674669 | K7: 0.42585408 | L7: 0.18390285 | M7: 0.15092363 | N7: 0.15054342 | O7: 0.16442343 | P7: 0.4094702 | Q7: 0.40523646 | R7: 0.0042337355 | S7: 0.11298586 | T7: 0.016383881 | U7: -0.0414548 | V7: 0.6459882 | W7: 0.3618771 | X7: 0.3769436 | Y7: 0.0150665 | Z7: 0.0396613 | AA7: 0.039079964 | AB7: 0.001384183 | AC7: 2.1845112e-05 | AD7: 0.033060625 | AE7: 0.00057615259 | AF7: 0.0011707275 | AG7: 0.055291126
A8: 0.50608909 | B8: 0.10667379 | C8: 0.47340094 | D8: 4.9741566 | E8: 0.24984392 | F8: 1.166025 | G8: 1.3595674 | H8: 0.050983596 | I8: 1.0758264 | J8: 0.76627491 | K8: 0.44126728 | L8: 0.20376224 | M8: 0.1509556 | N8: 0.15139278 | O8: 0.16332109 | P8: 0.41009199 | Q8: 0.40585825 | R8: 0.0042337386 | S8: 0.11298597 | T8: 0.031175297 | U8: -0.0414548 | V8: 0.6302466 | W8: 0.3481111 | X8: 0.3769156 | Y8: 0.0288045 | Z8: 0.06068911 | AA8: 0.033645938 | AB8: 0.015091362 | AC8: 1.7776426e-05 | AD8: 0.035421059 | AE8: 0.00059788577 | AF8: 0.0013413079 | AG8: 0.046626867
A9: 0.51322999 | B9: 0.10801434 | C9: 0.47425666 | D9: 5.0535173 | E9: 0.26574433 | F9: 1.1949486 | G9: 1.3910501 | H9: 0.051549126 | I9: 1.0957884 | J9: 0.77595688 | K9: 0.45085769 | L9: 0.21401246 | M9: 0.15099047 | N9: 0.15191042 | O9: 0.16228139 | P9: 0.41597432 | Q9: 0.4117406 | R9: 0.0042337228 | S9: 0.11298607 | T9: 0.034883371 | U9: -0.0414548 | V9: 0.6142008 | W9: 0.343093 | X9: 0.3752261 | Y9: 0.0321331 | Z9: 0.050927918 | AA9: -0.010107775 | AB9: 0.01072984 | AC9: 1.230622e-05 | AD9: -0.013831857 | AE9: 0.00040354371 | AF9: -0.00082698334 | AG9: 0.021895002
A10: 0.52834018 | B10: 0.103727 | C10: 0.46988321 | D10: 5.0872032 | E10: 0.22304314 | F10: 1.1686732 | G10: 1.3718167 | H10: 0.048989895 | I10: 1.0683943 | J10: 0.78646481 | K10: 0.42764582 | L10: 0.16883178 | M10: 0.15081045 | N10: 0.14995365 | O10: 0.16305708 | P10: 0.41728992 | Q10: 0.41305623 | R10: 0.0042336922 | S10: 0.11298613 | T10: 0.0103559 | U10: -0.0414548 | V10: 0.6470159 | W10: 0.3539436 | X10: 0.3630613 | Y10: 0.0091177 | Z10: -0.001225784 | AA10: 0.054546379 | AB10: 0.034865676 | AC10: 2.4699022e-05 | AD10: 0.023082198 | AE10: -0.00016099902 | AF10: 0.00089012673 | AG10: 0.047235221
A11: 0.53527979 | B11: 0.10827153 | C11: 0.47525233 | D11: 5.1569489 | E11: 0.26036524 | F11: 1.2234085 | G11: 1.4216276 | H11: 0.051530605 | I11: 1.110598 | J11: 0.81291677 | K11: 0.4455378 | L11: 0.18779634 | M11: 0.15017195 | N11: 0.15087119 | O11: 0.16254424 | P11: 0.42776344 | Q11: 0.42352971 | R11: 0.0042337303 | S11: 0.11298622 | T11: 0.017774357 | U11: -0.0414548 | V11: 0.624332 | W11: 0.3438254 | X11: 0.3596213 | Y11: 0.0157959 | Z11: 0.075315482 | AA11: 0.03131389 | AB11: 0.024728172 | AC11: 1.1150884e-05 | AD11: 0.038730067 | AE11: 0.00079345651 | AF11: 0.0015098436 | AG11: 0.026051328
A12: 0.5362848 | B12: 0.10838326 | C12: 0.47356964 | D12: 5.2387679 | E12: 0.27505188 | F12: 1.2404811 | G12: 1.4459093 | H12: 0.05127539 | I12: 1.1219529 | J12: 0.80961037 | K12: 0.45927977 | L12: 0.2109785 | M12: 0.1508641 | N12: 0.15186582 | O12: 0.16167485 | P12: 0.42914442 | Q12: 0.42491073 | R12: 0.0042336909 | S12: 0.11298627 | T12: 0.030135352 | U12: -0.0414548 | V12: 0.6063371 | W12: 0.3388876 | X12: 0.3662593 | Y12: 0.0273717 | Z12: 0.039730718 | AA12: 0.013593042 | AB12: 0.040697091 | AC12: 7.4673929e-06 | AD12: 0.03289997 | AE12: 0.00097552088 | AF12: 0.0013053444 | AG12: 0.030399828
A13: 0.53886066 | B13: 0.10613415 | C13: 0.47026917 | D13: 5.3031348 | E13: 0.26066565 | F13: 1.2358679 | G13: 1.4491291 | H13: 0.049725789 | I13: 1.1135378 | J13: 0.81573549 | K13: 0.46098143 | L13: 0.21435827 | M13: 0.15133051 | N13: 0.15206775 | O13: 0.16167756 | P13: 0.43634156 | Q13: 0.43210791 | R13: 0.0042336567 | S13: 0.11298629 | T13: 0.024639869 | U13: -0.0414548 | V13: 0.6161426 | W13: 0.3473745 | X13: 0.3695818 | Y13: 0.0222073 | Z13: 0.019241286 | AA13: 0.021744113 | AB13: 0.040581637 | AC13: 2.0459823e-06 | AD13: 0.021162403 | AE13: 9.7491485e-05 | AF13: 0.00098643967 | AG13: 0.0030681485
... A25: 0.48415649 | B25: 0.09883107 | C25: 0.46802539 | D25: 4.7981408 | E25: 0.15798132 | F25: 1.0648804 | G25: 1.2556814 | H25: 0.046877728 | I25: 0.99497309 | J25: 0.92978684 | K25: 0.42046242 | L25: 0.17256467 | M25: 0.15012201 | N25: 0.15036714 | O25: 0.17703336 | P25: 0.42274258 | Q25: 0.41850897 | R25: 0.0042336159 | S25: 0.11298525 | T25: -0.0022801603 | U25: -0.0414548 | V25: 0.8728384 | W25: 0.3970472 | X25: 0.3948536 | Y25: -0.0021936 | Z25: 0.033938883 | AA25: 0 | AB25: 0 | AC25: 0 | AD25: 0 | AE25: 0 | AF25: 0 | AG25: 0

Sheet Results
B1: Observado | AC1: Prognóstico
A2: Año | B2: =Smooth!A1 -> Consumo privado | C2: =Smooth!B1 -> Retorno do capital | D2: =Smooth!C1 -> Trabalho | E2: =Smooth!D1 -> Capital privado | F2: =Smooth!E1 -> Investimento privado | G2: =Smooth!F1 -> Produto | H2: =Smooth!G1 -> Taxa de salário | I2: =Smooth!H1 -> Taxa de retorno dos ativos financeiros | ... AA2: =Smooth!Z1 -> Crescimento do PIB | AC2: =Forecast!A1 -> Consumo privado | AD2: =Forecast!B1 -> Retorno do capital | AE2: =Forecast!C1 -> Trabalho | AF2: =Forecast!D1 -> Capital privado | AG2: =Forecast!E1 -> Investimento privado | AH2: =Forecast!F1 -> Produto | AI2: =Forecast!G1 -> Taxa de salário | AJ2: =Forecast!H1 -> Taxa de retorno dos ativos financeiros | ... BB2: =Forecast!Z1 -> Crescimento do PIB
A3: 2001 | B3: =Smooth!A2 -> 0.50386873 | C3: =Smooth!B2 -> 0.10236787 | D3: =Smooth!C2 -> 0.46959392 | E3: =Smooth!D2 -> 4.7195047 | F3: =Smooth!E2 -> 0.21045549 | G3: =Smooth!F2 -> 1.0704118 | H3: =Smooth!G2 -> 1.2580429 | I3: =Smooth!H2 -> 0.049098392 | ... AA3: =Smooth!Z2 -> 0.013852707
A4: 2002 | B4: =Smooth!A3 -> 0.46862452 | C4: =Smooth!B3 -> 0.10230525 | D4: =Smooth!C3 -> 0.46913479 | E4: =Smooth!D3 -> 4.7527826 | F4: =Smooth!E3 -> 0.21011961 | G4: =Smooth!F3 -> 1.0777328 | H4: =Smooth!G3 -> 1.2677717 | I4: =Smooth!H3 -> 0.048895277 | ... AA4: =Smooth!Z3 -> 0.030517091
A5: 2003 | B5: =Smooth!A4 -> 0.51672344 | C5: =Smooth!B4 -> 0.10032624 | D5: =Smooth!C4 -> 0.46598544 | E5: =Smooth!D4 -> 4.7780931 | F5: =Smooth!E4 -> 0.20339915 | G5: =Smooth!F4 -> 1.0648387 | H5: =Smooth!G4 -> 1.2609463 | I5: =Smooth!H4 -> 0.047673096 | ... AA5: =Smooth!Z4 -> 0.011417286
A6: 2004 | B6: =Smooth!A5 -> 0.50999463 | C6: =Smooth!B5 -> 0.10324632 | D6: =Smooth!C5 -> 0.46917536 | E6: =Smooth!D5 -> 4.827652 | F6: =Smooth!E5 -> 0.2285959 | G6: =Smooth!F5 -> 1.1008452 | H6: =Smooth!G5 -> 1.2946044 | I6: =Smooth!H5 -> 0.049265803 | ... AA6: =Smooth!Z5 -> 0.057620002
A7: 2005 | B7: =Smooth!A6 -> 0.49508696 | C7: =Smooth!B6 -> 0.10301609 | D7: =Smooth!C6 -> 0.46838488 | E7: =Smooth!D6 -> 4.8749107 | F7: =Smooth!E6 -> 0.22815276 | G7: =Smooth!F6 -> 1.1097711 | H7: =Smooth!G6 -> 1.3070668 | I7: =Smooth!H6 -> 0.048966678 | ... AA7: =Smooth!Z6 -> 0.032033435
A8: 2006 | B8: =Smooth!A7 -> 0.50132002 | C8: =Smooth!B7 -> 0.10361639 | D8: =Smooth!C7 -> 0.47092766 | E8: =Smooth!D7 -> 4.9082259 | F8: =Smooth!E7 -> 0.21597998 | G8: =Smooth!F7 -> 1.1267702 | H8: =Smooth!G7 -> 1.3202567 | I8: =Smooth!H7 -> 0.049383948 | ... AA8: =Smooth!Z7 -> 0.0396613
A9: 2007 | B9: =Smooth!A8 -> 0.5060891 | C9: =Smooth!B8 -> 0.10667379 | D9: =Smooth!C8 -> 0.47340094 | E9: =Smooth!D8 -> 4.9741566 | F9: =Smooth!E8 -> 0.24984392 | G9: =Smooth!F8 -> 1.166025 | H9: =Smooth!G8 -> 1.3595674 | I9: =Smooth!H8 -> 0.050983597 | ... AA9: =Smooth!Z8 -> 0.06068911
A10: 2008 | B10: =Smooth!A9 -> 0.51322999 | C10: =Smooth!B9 -> 0.10801434 | D10: =Smooth!C9 -> 0.47425666 | E10: =Smooth!D9 -> 5.0535173 | F10: =Smooth!E9 -> 0.26574433 | G10: =Smooth!F9 -> 1.1949486 | H10: =Smooth!G9 -> 1.3910501 | I10: =Smooth!H9 -> 0.051549126 | ... AA10: =Smooth!Z9 -> 0.050927918
A11: 2009 | B11: =Smooth!A10 -> 0.52834018 | C11: =Smooth!B10 -> 0.103727 | D11: =Smooth!C10 -> 0.46988321 | E11: =Smooth!D10 -> 5.0872032 | F11: =Smooth!E10 -> 0.22304314 | G11: =Smooth!F10 -> 1.1686732 | H11: =Smooth!G10 -> 1.3718167 | I11: =Smooth!H10 -> 0.048989896 | ... AA11: =Smooth!Z10 -> -0.001225784
A12: 2010 | B12: =Smooth!A11 -> 0.5352798 | C12: =Smooth!B11 -> 0.10827153 | D12: =Smooth!C11 -> 0.47525233 | E12: =Smooth!D11 -> 5.1569489 | F12: =Smooth!E11 -> 0.26036524 | G12: =Smooth!F11 -> 1.2234085 | H12: =Smooth!G11 -> 1.4216276 | I12: =Smooth!H11 -> 0.051530606 | ... AA12: =Smooth!Z11 -> 0.075315482
A13: 2011 | B13: =Smooth!A12 -> 0.5362848 | C13: =Smooth!B12 -> 0.10838326 | D13: =Smooth!C12 -> 0.47356964 | E13: =Smooth!D12 -> 5.2387679 | F13: =Smooth!E12 -> 0.27505187 | G13: =Smooth!F12 -> 1.2404811 | H13: =Smooth!G12 -> 1.4459093 | I13: =Smooth!H12 -> 0.051275391 | ... AA13: =Smooth!Z12 -> 0.039730718
A14: 2012 | B14: =Smooth!A13 -> 0.53886066 | C14: =Smooth!B13 -> 0.10613415 | D14: =Smooth!C13 -> 0.47026917 | E14: =Smooth!D13 -> 5.3031348 | F14: =Smooth!E13 -> 0.26066565 | G14: =Smooth!F13 -> 1.2358679 | H14: =Smooth!G13 -> 1.4491291 | I14: =Smooth!H13 -> 0.049725789 | ... AA14: =Smooth!Z13 -> 0.019241286
... A25: 2023 | B25: =Smooth!A24 -> 0.5027655 | C25: =Smooth!B24 -> 0.096661005 | D25: =Smooth!C24 -> 0.466524 | E25: =Smooth!D24 -> 4.8207966 | F25: =Smooth!E24 -> 0.13203221 | G25: =Smooth!F24 -> 1.0539378 | H25: =Smooth!G24 -> 1.2468382 | I25: =Smooth!H24 -> 0.045612413 | ... AA25: =Smooth!Z24 -> 0.032411622
A26: 2024 | B26: =Smooth!A25 -> 0.48415649 | C26: =Smooth!B25 -> 0.09883107 | D26: =Smooth!C25 -> 0.46802539 | E26: =Smooth!D25 -> 4.7981408 | F26: =Smooth!E25 -> 0.15798132 | G26: =Smooth!F25 -> 1.0648804 | H26: =Smooth!G25 -> 1.2556815 | I26: =Smooth!H25 -> 0.046877728 | ... AA26: =Smooth!Z25 -> 0.033938883 | AC26: =Forecast!A2 -> 0.48415649 | AD26: =Forecast!B2 -> 0.09883107 | AE26: =Forecast!C2 -> 0.46802539 | AF26: =Forecast!D2 -> 4.7981408 | AG26: =Forecast!E2 -> 0.15798132 | AH26: =Forecast!F2 -> 1.0648804 | AI26: =Forecast!G2 -> 1.2556815 | AJ26: =Forecast!H2 -> 0.046877728 | ... BB26: =Forecast!Z2 -> 0.033938883
A27: 2025 | AC27: =Forecast!A3 -> 0.48560506 | AD27: =Forecast!B3 -> 0.09925113 | AE27: =Forecast!C3 -> 0.46845888 | AF27: =Forecast!D3 -> 4.7803181 | AG27: =Forecast!E3 -> 0.16196559 | AH27: =Forecast!F3 -> 1.0640591 | AI27: =Forecast!G3 -> 1.2535951 | AJ27: =Forecast!H3 -> 0.047178451 | ... BB27: =Forecast!Z3 -> 0.022824009
A28: 2026 | AC28: =Forecast!A4 -> 0.48562091 | AD28: =Forecast!B4 -> 0.099594252 | AE28: =Forecast!C4 -> 0.46888068 | AF28: =Forecast!D4 -> 4.7659111 | AG28: =Forecast!E4 -> 0.1647134 | AH28: =Forecast!F4 -> 1.0635442 | AI28: =Forecast!G4 -> 1.2518963 | AJ28: =Forecast!H4 -> 0.047424712 | ... BB28: =Forecast!Z4 -> 0.023113519
A29: 2027 | AC29: =Forecast!A5 -> 0.48512495 | AD29: =Forecast!B5 -> 0.099879611 | AE29: =Forecast!C5 -> 0.46928161 | AF29: =Forecast!D5 -> 4.7539251 | AG29: =Forecast!E5 -> 0.16659458 | AH29: =Forecast!F5 -> 1.0632108 | AI29: =Forecast!G5 -> 1.2504633 | AJ29: =Forecast!H5 -> 0.047631292 | ... BB29: =Forecast!Z5 -> 0.023284951
A30: 2028 | AC30: =Forecast!A6 -> 0.48447489 | AD30: =Forecast!B6 -> 0.10012086 | AE30: =Forecast!C6 -> 0.46965395 | AF30: =Forecast!D6 -> 4.7437017 | AG30: =Forecast!E6 -> 0.16790801 | AH30: =Forecast!F6 -> 1.0629732 | AI30: =Forecast!G6 -> 1.2492166 | AJ30: =Forecast!H6 -> 0.047807663 | ... BB30: =Forecast!Z6 -> 0.023375523
A31: 2029 | AC31: =Forecast!A7 -> 0.48380629 | AD31: =Forecast!B7 -> 0.10032763 | AE31: =Forecast!C7 -> 0.46999418 | AF31: =Forecast!D7 -> 4.7348098 | AG31: =Forecast!E7 -> 0.16885654 | AH31: =Forecast!F7 -> 1.0627808 | AI31: =Forecast!G7 -> 1.2481062 | AJ31: =Forecast!H7 -> 0.047960205 | ... BB31: =Forecast!Z7 -> 0.023418233
A32: 2030 | AC32: =Forecast!A8 -> 0.48316765 | AD32: =Forecast!B8 -> 0.10050679 | AE32: =Forecast!C8 -> 0.47030208 | AF32: =Forecast!D8 -> 4.7269631 | AG32: =Forecast!E8 -> 0.16956847 | AH32: =Forecast!F8 -> 1.0626065 | AI32: =Forecast!G8 -> 1.247101 | AJ32: =Forecast!H8 -> 0.048093429 | ... BB32: =Forecast!Z8 -> 0.023435323
A33: 2031 | AC33: =Forecast!A9 -> 0.48257378 | AD33: =Forecast!B9 -> 0.10066341 | AE33: =Forecast!C9 -> 0.47057937 | AF33: =Forecast!D9 -> 4.7199648 | AG33: =Forecast!E9 -> 0.17012286 | AH33: =Forecast!F9 -> 1.0624372 | AI33: =Forecast!G9 -> 1.2461815 | AJ33: =Forecast!H9 -> 0.048210673 | ... BB33: =Forecast!Z9 -> 0.023440076
A34: 2032 | AC34: =Forecast!A10 -> 0.48202682 | AD34: =Forecast!B10 -> 0.10080129 | AE34: =Forecast!C10 -> 0.47082868 | AF34: =Forecast!D10 -> 4.7136742 | AG34: =Forecast!E10 -> 0.17056833 | AH34: =Forecast!F10 -> 1.0622677 | AI34: =Forecast!G10 -> 1.2453345 | AJ34: =Forecast!H10 -> 0.048314502 | ... BB34: =Forecast!Z10 -> 0.023439819
A35: 2033 | AC35: =Forecast!A11 -> 0.4815244 | AD35: =Forecast!B11 -> 0.10092342 | AE35: =Forecast!C11 -> 0.47105293 | AF35: =Forecast!D11 -> 4.7079862 | AG35: =Forecast!E11 -> 0.17093529 | AH35: =Forecast!F11 -> 1.0620966 | AI35: =Forecast!G11 -> 1.244551 | AJ35: =Forecast!H11 -> 0.048406943 | ... BB35: =Forecast!Z11 -> 0.023438314
A36: 2034 | AC36: =Forecast!A12 -> 0.48106285 | AD36: =Forecast!B12 -> 0.10103217 | AE36: =Forecast!C12 -> 0.47125496 | AF36: =Forecast!D12 -> 4.7028195 | AG36: =Forecast!E12 -> 0.17124336 | AH36: =Forecast!F12 -> 1.0619244 | AI36: =Forecast!G12 -> 1.2438241 | AJ36: =Forecast!H12 -> 0.048489632 | ... BB36: =Forecast!Z12 -> 0.023437319

Sheet Plots
